xhistogram/__init__.py
xhistogram/_version.py
xhistogram/core.py
xhistogram/xarray.py
xhistogram/test/__init__.py
xhistogram/test/fixtures.py
xhistogram/test/test_chunking.py
xhistogram/test/test_chunking_hypotheses.py
xhistogram/test/test_core.py
xhistogram/test/test_xarray.py
xhistogram-0.3.2.dist-info/LICENSE
xhistogram-0.3.2.dist-info/METADATA
xhistogram-0.3.2.dist-info/WHEEL
xhistogram-0.3.2.dist-info/top_level.txt
xhistogram-0.3.2.dist-info/RECORD
