Metadata-Version: 2.1
Name: xhistogram
Version: 0.3.2
Summary: Fast, flexible, label-aware histograms for numpy and xarray
Home-page: https://github.com/xgcm/xhistogram
Author: xhistogram Developers
Author-email: rpa@ldeo.columbia.edu
License: MIT
Classifier: Development Status :: 4 - Beta
Classifier: License :: OSI Approved :: Apache Software License
Classifier: Operating System :: OS Independent
Classifier: Intended Audience :: Science/Research
Classifier: Programming Language :: Python
Classifier: Programming Language :: Python :: 3
Classifier: Programming Language :: Python :: 3.7
Classifier: Programming Language :: Python :: 3.8
Classifier: Programming Language :: Python :: 3.9
Classifier: Topic :: Scientific/Engineering
Requires-Python: >=3.7
License-File: LICENSE
